molpharm/__init__.py
molpharm/example.py
molpharm-0.1.0.dist-info/METADATA
molpharm-0.1.0.dist-info/WHEEL
molpharm-0.1.0.dist-info/top_level.txt
molpharm-0.1.0.dist-info/RECORD
