Metadata-Version: 2.1
Name: molpharm
Version: 0.1.0
Summary: A brief description of your package
Home-page: https://github.com/yourusername/my-python-package
Author: George Mathew
Author-email: nerd2923@gmail.com
License: MIT
Classifier: Programming Language :: Python :: 3
Classifier: License :: OSI Approved :: MIT License
Classifier: Operating System :: OS Independent
Requires-Python: >=3.6
Provides-Extra: dev
Requires-Dist: pytest>=6.0; extra == "dev"
